{
    "key": "events/ev-eventexample.json",
    "v": 123,
    "value": "{\"tokens\":{\"publicToken\":\"eventexample\",\"moderatorToken\":\"eventexamplemod\"},\"data\":{\"maxLikes\":0,\"name\":\"Unity Meetup June 2017\",\"description\":\"Welcome to the Hamburg Unity Meetup June 2017. This time we would like to conduct a new format - instead of two presentations we would like to invite you in a very interactive panel discussion. Four People from various companies will face your questions from the audience in how they use Unity on a daily basis.\",\"shortUrl\":\"https://goo.gl/EAaWyA\",\"longUrl\":\"\"},\"questions\":[{\"id\":0,\"likes\":72,\"text\":\"Since when do you use Unity professionally?\",\"hidden\":false,\"answered\":false,\"createTimeUnix\":1515966750},{\"id\":1,\"likes\":64,\"text\":\"Common Pitfalls using Unity in your Area?\",\"hidden\":false,\"answered\":false,\"createTimeUnix\":1515966750},{\"id\":2,\"likes\":65,\"text\":\"Advice on how to use Unity in bigger longterm projects?\",\"hidden\":false,\"answered\":false,\"createTimeUnix\":1515966750},{\"id\":3,\"likes\":65,\"text\":\"Areas you would like to see changed or improved in unity?\",\"hidden\":false,\"answered\":false,\"createTimeUnix\":1515966750},{\"id\":4,\"likes\":74,\"text\":\"How do you see the Monopoly of Unity? Where is it heading, what risks do you see?\",\"hidden\":false,\"answered\":false,\"createTimeUnix\":1515966750},{\"id\":5,\"likes\":500,\"text\":\"What was the weirdest bug you had with unity?\",\"hidden\":false,\"answered\":false,\"createTimeUnix\":1515966750},{\"id\":6,\"likes\":67,\"text\":\"How does using unity affect the workflows in your team?\",\"hidden\":false,\"answered\":false,\"createTimeUnix\":1515966750},{\"id\":7,\"likes\":236,\"text\":\"How do you think Unity compares to other Engines?\",\"hidden\":false,\"answered\":false,\"createTimeUnix\":1515966750},{\"id\":8,\"likes\":96,\"text\":\"What usage do you see for Unity outside of games?\",\"hidden\":false,\"answered\":false,\"createTimeUnix\":1515966750},{\"id\":9,\"likes\":70,\"text\":\"What excites you the most on unity's roadmap? What upcoming feature?\",\"hidden\":false,\"answered\":false,\"createTimeUnix\":1515966750},{\"id\":10,\"likes\":156,\"text\":\"What is the most underappreciated feature of unity?\",\"hidden\":false,\"answered\":false,\"createTimeUnix\":1515966750},{\"id\":11,\"likes\":70,\"text\":\"What are your experiences with the Unity AssetStore?\",\"hidden\":false,\"answered\":false,\"createTimeUnix\":1515966750},{\"id\":12,\"likes\":65,\"text\":\"What experience do you have with the Unity Services like CloudBuild, Ads, Analytics, IAP?\",\"hidden\":false,\"answered\":false,\"createTimeUnix\":1515966750},{\"id\":13,\"likes\":2,\"text\":\"Who in the Community inspires you the most? Who do you follow?\",\"hidden\":false,\"answered\":true,\"createTimeUnix\":1515966750},{\"id\":14,\"likes\":2,\"text\":\"How do you use the Editor scripting feature of unity?\",\"hidden\":false,\"answered\":true,\"createTimeUnix\":1515966750},{\"id\":15,\"likes\":2,\"text\":\"What kind of tips can you give the audience on debugging and profiling in Unity?\",\"hidden\":false,\"answered\":true,\"createTimeUnix\":1515966750}],\"createTimeUTC\":\"20170808T153744\",\"createTimeUnix\":0,\"state\":{\"state\":1},\"deleteTimeUnix\":0,\"deleted\":false,\"lastEditUnix\":1667894990}"
}